campaign/__init__.py
campaign/apps.py
campaign/celery.py
campaign/conf.py
campaign/exceptions.py
campaign/signals.py
campaign/urls.py
campaign/admin/__init__.py
campaign/admin/campaign.py
campaign/management/__init__.py
campaign/management/commands/__init__.py
campaign/migrations/0001_initial.py
campaign/migrations/0002_auto_20181126_2151.py
campaign/migrations/0003_auto_20181207_1854.py
campaign/migrations/0004_endorsement_link.py
campaign/migrations/0005_auto_20181213_1924.py
campaign/migrations/__init__.py
campaign/models/__init__.py
campaign/models/campaign.py
campaign/models/endorsement.py
campaign/models/staffer.py
campaign/serializers/__init__.py
campaign/tasks/__init__.py
campaign/tasks/aws.py
campaign/templates/campaign/home.html
campaign/templatetags/__init__.py
campaign/utils/__init__.py
campaign/utils/api_auth.py
campaign/utils/auth.py
campaign/utils/aws.py
campaign/utils/importers.py
campaign/views/__init__.py
campaign/views/home.py
campaign/viewsets/__init__.py
politico_civic_campaign-0.2.1.dist-info/METADATA
politico_civic_campaign-0.2.1.dist-info/RECORD
politico_civic_campaign-0.2.1.dist-info/WHEEL
politico_civic_campaign-0.2.1.dist-info/top_level.txt
